circle/__init__.py
circle/web3/__init__.py
circle/web3/utils.py
circle_web3_sdk_util-9.1.0.dist-info/licenses/LICENSE
circle_web3_sdk_util-9.1.0.dist-info/METADATA
circle_web3_sdk_util-9.1.0.dist-info/WHEEL
circle_web3_sdk_util-9.1.0.dist-info/top_level.txt
circle_web3_sdk_util-9.1.0.dist-info/RECORD
