Metadata-Version: 2.4
Name: circle-web3-sdk-util
Version: 9.1.0
Summary: The Python SDK Utility for Circle Web3 Services
Home-page: https://github.com/circlefin/circle-web3-python-sdk
Author: Circle Technology Inc
Author-email: bohan.li@circle.com
License: MIT License
Project-URL: Source, https://github.com/circlefin/circle-web3-python-sdk
Project-URL: Developer Doc, https://developers.circle.com/w3s/
Keywords: Circle,Web3,Python,Developer Controlled Wallets,User Controlled Wallets,Smart Contract Platform
Requires-Python: >=3.10,<4
License-File: LICENSE
Requires-Dist: pycryptodome>=3.20.0
Dynamic: author
Dynamic: author-email
Dynamic: description
Dynamic: description-content-type
Dynamic: home-page
Dynamic: keywords
Dynamic: license
Dynamic: license-file
Dynamic: project-url
Dynamic: requires-dist
Dynamic: requires-python
Dynamic: summary
